outlier_101883071/__init__.py
outlier_101883071/outlier_101883071.py
outlier_101883071-1.0.1.dist-info/LICENSE
outlier_101883071-1.0.1.dist-info/METADATA
outlier_101883071-1.0.1.dist-info/WHEEL
outlier_101883071-1.0.1.dist-info/entry_points.txt
outlier_101883071-1.0.1.dist-info/top_level.txt
outlier_101883071-1.0.1.dist-info/RECORD
