Metadata-Version: 2.1
Name: outlier-101883071
Version: 1.0.1
Summary: Python package to remove outliers from dataset
Home-page: https://github.com/
Author: Yogesh
Author-email: ysingla001@gmail.com
License: MIT
Platform: UNKNOWN
Classifier: License :: OSI Approved :: MIT License
Classifier: Programming Language :: Python :: 3
Classifier: Programming Language :: Python :: 3.7
